{
  "Parent": "Scythe_Iron",
  "TranslationProperties": {
    "Name": "items.Tool_Scythe_Adamantite.name",
    "Description": "items.Tool_Scythe.description"
  },
  "Categories": [
    "Items.Tools"
  ],
  "Set": "Tool_Iron",
  "Quality": "Rare",
  "MaxStack": 1,
  "ItemLevel": 1,
  "Recipe": {
    "TimeSeconds": 1.5,
    "Input": [
      {
        "ResourceTypeId": "Wood_Trunk",
        "Quantity": 4
      },
      {
        "ResourceTypeId": "Ingredient_Bar_Adamantite",
        "Quantity": 5
      }
    ],
    "BenchRequirement": [
      {
        "Type": "Crafting",
        "Categories": [
          "Farming"
        ],
        "Id": "Farmingbench",
        "RequiredTierLevel": 10
      }
    ]
  },
  "MaxDurability": 800,
  "PlayerAnimationsId": "Battleaxe",
  "Model": "Items/Tools/Scythe/Adamantite.blockymodel",
  "Texture": "Items/Tools/Scythe/Adamantite_Texture.png",
  "IconProperties": {
    "Scale": 0.17,
    "Rotation": [
      45,
      300,
      0
    ],
    "Translation": [
      57,
      -41
    ]
  },
  "DroppedItemAnimation": "Items/Animations/Dropped/Dropped_Diagonal_Left.blockyanim",
  "Tags": {
    "Type": [
      "Tool"
    ]
  },
  "ItemSoundSetId": "ISS_Weapons_Wood",
  "Utility": {
    "Compatible": true
  },
  "InteractionVars": {
    "Radial_Harvest": {
      "Interactions": [
        {
          "Type": "Radial_Harvest",
          "Reach": 9.5
        }
      ]
    }
  },
  "Scale": 1,
  "Icon": "Icons/ItemsGenerated/Scythe_Adamantite.png"
}
